optable/LpModel.py
optable/OptModel.py
optable/QpModel.py
optable/Result.py
optable/TransportationModel.py
optable/__init__.py
optable-0.2.2.dist-info/LICENSE
optable-0.2.2.dist-info/METADATA
optable-0.2.2.dist-info/WHEEL
optable-0.2.2.dist-info/top_level.txt
optable-0.2.2.dist-info/RECORD
